csirtg_mail/__init__.py
csirtg_mail/_version.py
csirtg_mail/client.py
csirtg_mail/constants.py
csirtg_mail/parse.py
csirtg_mail/urls.py
csirtg_mail-0.0.0a8.dist-info/DESCRIPTION.rst
csirtg_mail-0.0.0a8.dist-info/METADATA
csirtg_mail-0.0.0a8.dist-info/RECORD
csirtg_mail-0.0.0a8.dist-info/WHEEL
csirtg_mail-0.0.0a8.dist-info/entry_points.txt
csirtg_mail-0.0.0a8.dist-info/metadata.json
csirtg_mail-0.0.0a8.dist-info/top_level.txt
test/__init__.py
test/test_multi_alternative_plain_html_01.py
test/test_multi_alternative_plain_html_02.py
test/test_multi_alternative_plain_html_03.py
test/test_multi_alternative_plain_text_01.py
test/test_multi_mixed_alternative_plain_html_01.py
test/test_multi_mixed_html_application_octet-stream_01.py
test/test_multi_mixed_plain_application_x_zip_compressed_01.py
test/test_multi_mixed_plain_rfc822_mixed_plain_rfc822_plain_01.py
test/test_multi_mixed_plain_rfc822_plain_01.py
test/test_multi_mixed_plain_rfc822_plain_02.py
test/test_single_html_01.py
test/test_single_html_02.py
test/test_single_html_03.py
test/test_single_html_04.py
test/test_single_plain_01.py
test/test_single_plain_02.py
test/test_single_plain_03.py
