Metadata-Version: 2.0
Name: csirtg-mail
Version: 0.0.0a8
Summary: the fastest way to parse mail
Home-page: https://github.com/csirtgadgets/csirtg-mail-py
Author: Wes Young
Author-email: wes@csirtgadgets.org
License: LGPL3
Keywords: security
Platform: UNKNOWN
Classifier: Topic :: System :: Networking
Classifier: Environment :: Other Environment
Classifier: Intended Audience :: Developers
Classifier: License :: OSI Approved :: GNU Lesser General Public License v3 (LGPLv3)
Classifier: Programming Language :: Python
Requires-Dist: beautifulsoup4 (>=4.4.0,<4.5)
Requires-Dist: chardet (>=2.3.0)
Requires-Dist: html5lib (==1.0b8)
Requires-Dist: lxml (>=3.5.0,<4.0)
Requires-Dist: pyzmail (>=1.0.3,<2.0)
